{"areacd":"E06000001","rank_localauthority_2004":17,"rank_localauthority_2005":17,"rank_localauthority_2006":24,"rank_localauthority_2007":27,"rank_localauthority_2008":31,"rank_localauthority_2009":44,"rank_localauthority_2010":63,"rank_localauthority_2011":95,"rank_localauthority_2012":103,"rank_localauthority_2013":90,"rank_localauthority_2014":81,"rank_localauthority_2015":71,"rank_localauthority_2016":71,"rank_localauthority_2017":77,"rank_localauthority_2018":93,"rank_localauthority_2019":113,"rank_localauthority_2020":129}
