{"areacd":"E07000075","rank_localauthority_2004":63,"rank_localauthority_2005":72,"rank_localauthority_2006":62,"rank_localauthority_2007":72,"rank_localauthority_2008":60,"rank_localauthority_2009":49,"rank_localauthority_2010":26,"rank_localauthority_2011":14,"rank_localauthority_2012":9,"rank_localauthority_2013":14,"rank_localauthority_2014":36,"rank_localauthority_2015":56,"rank_localauthority_2016":87,"rank_localauthority_2017":83,"rank_localauthority_2018":90,"rank_localauthority_2019":83,"rank_localauthority_2020":86}
