{"areacd":"E09000003","rank_localauthority_2004":307,"rank_localauthority_2005":308,"rank_localauthority_2006":293,"rank_localauthority_2007":280,"rank_localauthority_2008":268,"rank_localauthority_2009":259,"rank_localauthority_2010":255,"rank_localauthority_2011":267,"rank_localauthority_2012":278,"rank_localauthority_2013":282,"rank_localauthority_2014":283,"rank_localauthority_2015":281,"rank_localauthority_2016":281,"rank_localauthority_2017":270,"rank_localauthority_2018":279,"rank_localauthority_2019":289,"rank_localauthority_2020":298}
