{"areacd":"E09000030","rank_localauthority_2003":28,"rank_localauthority_2004":35,"rank_localauthority_2005":52,"rank_localauthority_2006":55,"rank_localauthority_2007":55,"rank_localauthority_2008":48,"rank_localauthority_2009":53,"rank_localauthority_2010":63,"rank_localauthority_2011":84,"rank_localauthority_2012":76,"rank_localauthority_2013":114,"rank_localauthority_2014":102,"rank_localauthority_2015":109,"rank_localauthority_2016":96,"rank_localauthority_2017":162,"rank_localauthority_2018":180}
