{"areacd":"E09000016","rank_localauthority_2003":195,"rank_localauthority_2004":189,"rank_localauthority_2005":202,"rank_localauthority_2006":214,"rank_localauthority_2007":203,"rank_localauthority_2008":216,"rank_localauthority_2009":229,"rank_localauthority_2010":243,"rank_localauthority_2011":263,"rank_localauthority_2012":246,"rank_localauthority_2013":245,"rank_localauthority_2014":240,"rank_localauthority_2015":271,"rank_localauthority_2016":272,"rank_localauthority_2017":270,"rank_localauthority_2018":252}
