{"areacd":"E07000219","rank_localauthority_1997":26,"rank_localauthority_1998":19,"rank_localauthority_1999":23,"rank_localauthority_2000":27,"rank_localauthority_2001":32,"rank_localauthority_2002":32,"rank_localauthority_2003":42,"rank_localauthority_2004":44,"rank_localauthority_2005":32,"rank_localauthority_2006":36,"rank_localauthority_2007":26,"rank_localauthority_2008":36,"rank_localauthority_2009":44,"rank_localauthority_2010":39,"rank_localauthority_2011":46,"rank_localauthority_2012":56,"rank_localauthority_2013":70,"rank_localauthority_2014":74,"rank_localauthority_2015":88,"rank_localauthority_2016":95,"rank_localauthority_2017":91,"rank_localauthority_2018":88,"rank_localauthority_2019":95,"rank_localauthority_2020":96}
