{"areacd":"E07000078","rank_localauthority_1997":253,"rank_localauthority_1998":243,"rank_localauthority_1999":246,"rank_localauthority_2000":248,"rank_localauthority_2001":245,"rank_localauthority_2002":229,"rank_localauthority_2003":224,"rank_localauthority_2004":232,"rank_localauthority_2005":244,"rank_localauthority_2006":243,"rank_localauthority_2007":239,"rank_localauthority_2008":242,"rank_localauthority_2009":230,"rank_localauthority_2010":238,"rank_localauthority_2011":237,"rank_localauthority_2012":234,"rank_localauthority_2013":240,"rank_localauthority_2014":256,"rank_localauthority_2015":251,"rank_localauthority_2016":250,"rank_localauthority_2017":246,"rank_localauthority_2018":257,"rank_localauthority_2019":259,"rank_localauthority_2020":259}
