{"areacd":"E07000175","rank_localauthority_1997":215,"rank_localauthority_1998":230,"rank_localauthority_1999":223,"rank_localauthority_2000":238,"rank_localauthority_2001":226,"rank_localauthority_2002":239,"rank_localauthority_2003":235,"rank_localauthority_2004":243,"rank_localauthority_2005":234,"rank_localauthority_2006":225,"rank_localauthority_2007":241,"rank_localauthority_2008":238,"rank_localauthority_2009":225,"rank_localauthority_2010":209,"rank_localauthority_2011":198,"rank_localauthority_2012":190,"rank_localauthority_2013":181,"rank_localauthority_2014":193,"rank_localauthority_2015":209,"rank_localauthority_2016":194,"rank_localauthority_2017":187,"rank_localauthority_2018":201,"rank_localauthority_2019":203,"rank_localauthority_2020":194}
