{"areacd":"E07000173","rank_localauthority_2001":231,"rank_localauthority_2002":231,"rank_localauthority_2003":229,"rank_localauthority_2004":229,"rank_localauthority_2005":229,"rank_localauthority_2006":228,"rank_localauthority_2007":228,"rank_localauthority_2008":227,"rank_localauthority_2009":227,"rank_localauthority_2010":227,"rank_localauthority_2011":227,"rank_localauthority_2012":227,"rank_localauthority_2013":227,"rank_localauthority_2014":228,"rank_localauthority_2015":227,"rank_localauthority_2016":227,"rank_localauthority_2017":228,"rank_localauthority_2018":228,"rank_localauthority_2019":228,"rank_localauthority_2020":228}
