{"areacd":"E08000026","rank_localauthority_2001":323,"rank_localauthority_2002":322,"rank_localauthority_2003":320,"rank_localauthority_2004":317,"rank_localauthority_2005":315,"rank_localauthority_2006":315,"rank_localauthority_2007":315,"rank_localauthority_2008":315,"rank_localauthority_2009":315,"rank_localauthority_2010":315,"rank_localauthority_2011":317,"rank_localauthority_2012":320,"rank_localauthority_2013":321,"rank_localauthority_2014":324,"rank_localauthority_2015":326,"rank_localauthority_2016":326,"rank_localauthority_2017":328,"rank_localauthority_2018":328,"rank_localauthority_2019":328,"rank_localauthority_2020":330}
