{"areacd":"S12000033","rank_localauthority_2001":246,"rank_localauthority_2002":246,"rank_localauthority_2003":246,"rank_localauthority_2004":245,"rank_localauthority_2005":245,"rank_localauthority_2006":245,"rank_localauthority_2007":246,"rank_localauthority_2008":246,"rank_localauthority_2009":246,"rank_localauthority_2010":246,"rank_localauthority_2011":246,"rank_localauthority_2012":246,"rank_localauthority_2013":246,"rank_localauthority_2014":246,"rank_localauthority_2015":246,"rank_localauthority_2016":246,"rank_localauthority_2017":246,"rank_localauthority_2018":246,"rank_localauthority_2019":246,"rank_localauthority_2020":246}
