{"areacd":"E07000245","rank_localauthority_2001":247,"rank_localauthority_2002":247,"rank_localauthority_2003":248,"rank_localauthority_2004":249,"rank_localauthority_2005":248,"rank_localauthority_2006":247,"rank_localauthority_2007":249,"rank_localauthority_2008":249,"rank_localauthority_2009":250,"rank_localauthority_2010":251,"rank_localauthority_2011":251,"rank_localauthority_2012":251,"rank_localauthority_2013":249,"rank_localauthority_2014":252,"rank_localauthority_2015":253,"rank_localauthority_2016":251,"rank_localauthority_2017":252,"rank_localauthority_2018":251,"rank_localauthority_2019":249,"rank_localauthority_2020":245}
