{"areacd":"E09000027","rank_localauthority_2001":265,"rank_localauthority_2002":266,"rank_localauthority_2003":267,"rank_localauthority_2004":267,"rank_localauthority_2005":268,"rank_localauthority_2006":268,"rank_localauthority_2007":267,"rank_localauthority_2008":267,"rank_localauthority_2009":268,"rank_localauthority_2010":268,"rank_localauthority_2011":268,"rank_localauthority_2012":267,"rank_localauthority_2013":267,"rank_localauthority_2014":267,"rank_localauthority_2015":267,"rank_localauthority_2016":266,"rank_localauthority_2017":266,"rank_localauthority_2018":266,"rank_localauthority_2019":267,"rank_localauthority_2020":267}
