{"areacd":"S12000042","rank_localauthority_2001":232,"rank_localauthority_2002":230,"rank_localauthority_2003":227,"rank_localauthority_2004":224,"rank_localauthority_2005":223,"rank_localauthority_2006":221,"rank_localauthority_2007":220,"rank_localauthority_2008":220,"rank_localauthority_2009":219,"rank_localauthority_2010":219,"rank_localauthority_2011":219,"rank_localauthority_2012":219,"rank_localauthority_2013":220,"rank_localauthority_2014":218,"rank_localauthority_2015":216,"rank_localauthority_2016":214,"rank_localauthority_2017":213,"rank_localauthority_2018":210,"rank_localauthority_2019":209,"rank_localauthority_2020":205}
