{"areacd":"E07000140","rank_localauthority_2001":358,"rank_localauthority_2002":355,"rank_localauthority_2003":352,"rank_localauthority_2004":348,"rank_localauthority_2005":348,"rank_localauthority_2006":343,"rank_localauthority_2007":336,"rank_localauthority_2008":326,"rank_localauthority_2009":320,"rank_localauthority_2010":317,"rank_localauthority_2011":317,"rank_localauthority_2012":317,"rank_localauthority_2013":313,"rank_localauthority_2014":308,"rank_localauthority_2015":304,"rank_localauthority_2016":293,"rank_localauthority_2017":284,"rank_localauthority_2018":284,"rank_localauthority_2019":283,"rank_localauthority_2020":284}
