{"areacd":"E07000087","rank_localauthority_2001":276,"rank_localauthority_2002":278,"rank_localauthority_2003":279,"rank_localauthority_2004":285,"rank_localauthority_2005":294,"rank_localauthority_2006":302,"rank_localauthority_2007":299,"rank_localauthority_2008":298,"rank_localauthority_2009":298,"rank_localauthority_2010":297,"rank_localauthority_2011":296,"rank_localauthority_2012":292,"rank_localauthority_2013":285,"rank_localauthority_2014":285,"rank_localauthority_2015":284,"rank_localauthority_2016":284,"rank_localauthority_2017":286,"rank_localauthority_2018":290,"rank_localauthority_2019":295,"rank_localauthority_2020":299}
